mycalculator_SD/__init__.py
mycalculator_SD-0.1.dist-info/LICENCE.txt
mycalculator_SD-0.1.dist-info/METADATA
mycalculator_SD-0.1.dist-info/WHEEL
mycalculator_SD-0.1.dist-info/top_level.txt
mycalculator_SD-0.1.dist-info/RECORD
